LICENSE
MANIFEST.in
README.md
ez_setup.py
setup.py
nebgbhist/__init__.py
nebgbhist/apply.py
nebgbhist/fetch.py
nebgbhist/history.py
nebgbhist/validate.py
nebgbhist.egg-info/PKG-INFO
nebgbhist.egg-info/SOURCES.txt
nebgbhist.egg-info/dependency_links.txt
nebgbhist.egg-info/entry_points.txt
nebgbhist.egg-info/not-zip-safe
nebgbhist.egg-info/requires.txt
nebgbhist.egg-info/top_level.txt